pyshaho/An_Wb.py
pyshaho/Socket.py
pyshaho/__init__.py
pyshaho/encryption.py
pyshaho/mb.py
pyshaho-1.0.0.dist-info/LICENCE
pyshaho-1.0.0.dist-info/METADATA
pyshaho-1.0.0.dist-info/WHEEL
pyshaho-1.0.0.dist-info/top_level.txt
pyshaho-1.0.0.dist-info/RECORD
